emnify/__init__.py
emnify/api_manager.py
emnify/constants.py
emnify/emnify.py
emnify/errors.py
emnify/version.py
emnify/modules/__init__.py
emnify/modules/api/__init__.py
emnify/modules/api/models.py
emnify/modules/device/__init__.py
emnify/modules/device/api_call_manager.py
emnify/modules/device/manager.py
emnify/modules/device/models.py
emnify/modules/operator/__init__.py
emnify/modules/operator/api_call_manager.py
emnify/modules/operator/manager.py
emnify/modules/operator/models.py
emnify/modules/sim/__init__.py
emnify/modules/sim/api_call_manager.py
emnify/modules/sim/manager.py
emnify/modules/sim/models.py
emnify_sdk-0.5.0.dist-info/LICENSE
emnify_sdk-0.5.0.dist-info/METADATA
emnify_sdk-0.5.0.dist-info/WHEEL
emnify_sdk-0.5.0.dist-info/top_level.txt
emnify_sdk-0.5.0.dist-info/RECORD
