Metadata-Version: 2.1
Name: emnify-sdk
Version: 0.5.0
Summary: Supply your swarm of IoT Devices with cloud connectivity by EMnify. Automate your routines with this SDK for Python.
Home-page: https://github.com/EMnify/emnify-sdk-python
Author: EMnify
Author-email: 
Project-URL: Bug Tracker, https://github.com/EMnify/emnify-sdk-python
Keywords: Swagger,EMnify Python SDK,IoT
Requires-Python: >=3.9
License-File: LICENSE
Requires-Dist: requests<2.33.0,>=2.27.0
Requires-Dist: urllib3<1.27,>=1.21.1
Requires-Dist: pydantic<2.0.0,>=1.9.0
